MkRecClient/__init__.py
MkRecClient/example.py
MkRecClient-0.0.3.dist-info/LICENSE
MkRecClient-0.0.3.dist-info/METADATA
MkRecClient-0.0.3.dist-info/WHEEL
MkRecClient-0.0.3.dist-info/top_level.txt
MkRecClient-0.0.3.dist-info/RECORD
